itaxotools/haplostats/__init__.py
itaxotools/haplostats/counters.py
itaxotools/haplostats/haplostats.py
itaxotools/haplostats/indexer.py
itaxotools/haplostats/sets.py
itaxotools_haplostats-0.2.1.dist-info/LICENSE.txt
itaxotools_haplostats-0.2.1.dist-info/METADATA
itaxotools_haplostats-0.2.1.dist-info/WHEEL
itaxotools_haplostats-0.2.1.dist-info/top_level.txt
itaxotools_haplostats-0.2.1.dist-info/RECORD
